{
  "site": "WEEKLY EQUITY DESK",
  "subtitle": "미국주식 주간 리포트 · 기업가치 · 성장성 · 횡보",
  "next_pick": "발굴 중",
  "next_publish": "2026-07-12 22:00 KST",
  "reports": [
    {
      "no": 8,
      "ticker": "GILD",
      "company": "Gilead Sciences, Inc.",
      "date": "2026-07-04",
      "file": "GILD_2026-07-04.html",
      "price": "$131.27",
      "tldr": "HIV +10%·Yeztugo 가이던스 $1B 상향 vs $11.5B 온콜로지 베팅으로 FY26 EPS 손실 전환 · 8/27 BIC/LEN PDUFA · 6월 조정 후 52주 중하단 반등 시도",
      "value": "저평가",
      "growth": "가속·논쟁",
      "trend": "반등 시도"
    },
    {
      "no": 7,
      "ticker": "ADBE",
      "company": "Adobe Inc.",
      "date": "2026-06-28",
      "file": "ADBE_2026-06-28.html",
      "price": "$202.73",
      "tldr": "Q2 매출 +13%·AI ARR 3배 돌파·$25B 자사주 vs CEO·CFO 동시 공백·AI 네이티브 잠식 · 52주 최하단 6% 극단 저평가 바닥 탐색",
      "value": "극단 저평가",
      "growth": "AI 가속·논쟁",
      "trend": "바닥 탐색"
    },
    {
      "no": 6,
      "ticker": "CMCSA",
      "company": "Comcast Corporation",
      "date": "2026-06-21",
      "file": "CMCSA_2026-06-21.html",
      "price": "$24.50",
      "tldr": "EV/EBITDA 역대 최저 4.81배·FCF 수익률 15.6% · Peacock Q2 첫 흑자 전환 목전 · 브로드밴드 손실 4년 만에 첫 YoY 개선 vs. FWA 구조적 위협 · 52주 최하단 10% 바닥 탐색",
      "value": "극단 저평가",
      "growth": "논쟁",
      "trend": "바닥 탐색"
    },
    {
      "no": 5,
      "ticker": "PDD",
      "company": "PDD Holdings Inc.",
      "date": "2026-06-14",
      "file": "PDD_2026-06-14.html",
      "price": "$87.96",
      "tldr": "메가캡 e커머스 최저 EV/EBITDA 5.7배 · 딥 트랜스포메이션(매출 +11% vs 순이익 −15%) · 52주 최하단 바닥 탐색",
      "value": "저평가",
      "growth": "논쟁",
      "trend": "바닥 탐색"
    },
    {
      "no": 4,
      "ticker": "CTSH",
      "company": "Cognizant Technology Solutions Corp.",
      "date": "2026-06-07",
      "file": "CTSH_2026-06-07.html",
      "price": "$53.40",
      "tldr": "선행 PER 9.4배·EV/EBITDA 6.4배로 싸다 · AI가 위협이냐 기회냐 성장 논쟁(대형딜 TCV +70%) · YTD −34% 후 $51–$56 박스권",
      "value": "저평가",
      "growth": "논쟁",
      "trend": "횡보"
    },
    {
      "no": 3,
      "ticker": "QCOM",
      "company": "Qualcomm Incorporated",
      "date": "2026-06-03",
      "file": "QCOM_2026-06-03.html",
      "price": "$229",
      "tldr": "애플 모뎀 이별 충격 선반영 · 자동차(+38%)·AI 성장 논쟁 · 주가 이미 컨센서스 27% 상회 · $210–$245 박스권",
      "value": "논쟁",
      "growth": "전환 중",
      "trend": "횡보"
    },
    {
      "no": 2,
      "ticker": "PFE",
      "company": "Pfizer Inc.",
      "date": "2026-06-03",
      "file": "PFE_2026-06-03.html",
      "price": "$26.18",
      "tldr": "선행 PER 8.7배·배당 6.5%로 싸다 · 성장은 논쟁(온콜로지 vs 특허만료) · $23–$29 박스권",
      "value": "매력적",
      "growth": "논쟁 중",
      "trend": "횡보"
    },
    {
      "no": 1,
      "ticker": "PYPL",
      "company": "PayPal Holdings, Inc.",
      "date": "2026-06-03",
      "file": "PYPL_2026-06-03.html",
      "price": "$44.53",
      "tldr": "싸다(PER 8.5배·FCF 13%) · 성장은 멈췄다(EPS 보합) · 그래서 박스권",
      "value": "저평가",
      "growth": "정체",
      "trend": "횡보"
    }
  ]
}
